mojogpt/__init__.py
mojogpt/main.py
mojogpt-0.0.1.dist-info/METADATA
mojogpt-0.0.1.dist-info/WHEEL
mojogpt-0.0.1.dist-info/licenses/LICENSE.txt
mojogpt-0.0.1.dist-info/RECORD
